[
  [
    {
      "question": "What are they sending to the edge of space?",
      "answer": "Garlic bread."
    },
    {
      "question": "Why are they sending garlic bread?",
      "answer": "Because it's delicious and someone already sent pizza up in a balloon."
    },
    {
      "question": "What is the purpose of sending objects on balloons?",
      "answer": "Mostly as publicity stunts."
    }
  ],
  [
    {
      "question": "What object are they sending to the edge of space?",
      "answer": "Garlic bread."
    },
    {
      "question": "Why are they sending garlic bread to the edge of space?",
      "answer": "Because it's delicious and someone has already sent pizza up in a balloon before."
    },
    {
      "question": "What do they expect to happen to the garlic bread in space?",
      "answer": "It may freeze and be in near-vacuum."
    }
  ],
  [
    {
      "question": "What were Barry and the speaker doing?",
      "answer": "Chasing the payload and looking for a place to park."
    },
    {
      "question": "What did the speaker say about the cameras?",
      "answer": "They're still running."
    },
    {
      "question": "Who did the speaker thank at the end?",
      "answer": "Steve Randall from Random Aerospace and Barry Lewis from My Virgin Kitchen."
    }
  ]
]